[
  {
    "videoId": "qJBz2KmPLQU",
    "title": "재개발 투자한다면?, 한남 vs 성수 | 빌딩의 신 선택은?",
    "thumbnail": "https://i.ytimg.com/vi/qJBz2KmPLQU/sddefault.jpg",
    "publishedAt": "2025-09-28T03:01:02Z",
    "viewCount": 8144,
    "duration": "PT1M1S"
  },
  {
    "videoId": "80xkvsUDaPw",
    "title": "[데일리 이슈] 정책의 목표는 폭락이 아닌 '안정·성장', 투자는 '타이밍'이다",
    "thumbnail": "https://i.ytimg.com/vi/80xkvsUDaPw/sddefault.jpg",
    "publishedAt": "2025-08-11T05:45:00Z",
    "viewCount": 1851,
    "duration": "PT11M19S"
  },
  {
    "videoId": "maMEZuY7UJY",
    "title": "[데일리 이슈] 주택 리츠 사업은 투자에 어떤 영향을 미칠까?",
    "thumbnail": "https://i.ytimg.com/vi/maMEZuY7UJY/sddefault.jpg",
    "publishedAt": "2024-12-06T02:00:32Z",
    "viewCount": 505,
    "duration": "PT6M14S"
  },
  {
    "videoId": "m8335PQLq40",
    "title": "2023년도 부동산정책 방향 이렇게 갈 겁니다",
    "thumbnail": "https://i.ytimg.com/vi/m8335PQLq40/sddefault.jpg",
    "publishedAt": "2022-12-19T08:56:27Z",
    "viewCount": 24,
    "duration": "PT5M44S"
  },
  {
    "videoId": "R_owBu3Pn94",
    "title": "입주 전 사전점검, 전문가들이 알려주지 않는 꿀팁",
    "thumbnail": "https://i.ytimg.com/vi/R_owBu3Pn94/sddefault.jpg",
    "publishedAt": "2024-05-25T03:00:15Z",
    "viewCount": 1501,
    "duration": "PT6M29S"
  },
  {
    "videoId": "ea5QVKreWmU",
    "title": "빌딩의 신님의 2번째 LIVE 방송ㅣ오늘은 점심시간에 얘기 나눠요",
    "thumbnail": "https://i.ytimg.com/vi/ea5QVKreWmU/sddefault.jpg",
    "publishedAt": "2023-02-10T21:00:30Z",
    "viewCount": 1175,
    "duration": "PT49M5S"
  },
  {
    "videoId": "91r2hhrBWd4",
    "title": "#빌딩의신 21번째 라이브방송, 무엇이든 물어보세요 구독자 답변 모음ZIP!",
    "thumbnail": "https://i.ytimg.com/vi/91r2hhrBWd4/sddefault.jpg",
    "publishedAt": "2023-11-26T03:00:06Z",
    "viewCount": 1319,
    "duration": "PT18M14S"
  },
  {
    "videoId": "8yfvMMpTb90",
    "title": "#라이브방송 230524 빌딩의 신 9번째 LIVE 2부",
    "thumbnail": "https://i.ytimg.com/vi/8yfvMMpTb90/sddefault.jpg",
    "publishedAt": "2023-05-30T21:00:07Z",
    "viewCount": 1336,
    "duration": "PT23M8S"
  },
  {
    "videoId": "bI0sFh9lj_0",
    "title": "부동산 임장 전 필독 영상｜빌딩의 신 '임장 꿀팁' 대방출",
    "thumbnail": "https://i.ytimg.com/vi/bI0sFh9lj_0/sddefault.jpg",
    "publishedAt": "2023-07-15T23:00:16Z",
    "viewCount": 2240,
    "duration": "PT6M15S"
  },
  {
    "videoId": "zhdO6-92Spk",
    "title": "늙어가는 서울, 주택노후화ㅣ240424 #빌딩의신 40번째 LIVE 소통방송",
    "thumbnail": "https://i.ytimg.com/vi/zhdO6-92Spk/sddefault.jpg",
    "publishedAt": "2024-04-24T15:49:47Z",
    "viewCount": 1673,
    "duration": "PT1H6M16S"
  },
  {
    "videoId": "FauN5l9Fp70",
    "title": "[데일리 이슈] 부동산 생명이 있다! | 투자는 변화에 대응하는 노력이 필요하다.",
    "thumbnail": "https://i.ytimg.com/vi/FauN5l9Fp70/sddefault.jpg",
    "publishedAt": "2024-11-28T00:00:09Z",
    "viewCount": 1333,
    "duration": "PT5M19S"
  },
  {
    "videoId": "Wu7voB2u-pE",
    "title": "[데일리 이슈] 미국은 금리 인하! | 11월 한국도..?",
    "thumbnail": "https://i.ytimg.com/vi/Wu7voB2u-pE/sddefault.jpg",
    "publishedAt": "2024-11-08T01:15:03Z",
    "viewCount": 1437,
    "duration": "PT6M54S"
  },
  {
    "videoId": "3VA_qTtnkt4",
    "title": "[데일리 이슈] 재건축 단지 상가, 왜 텅 비어 있을까?",
    "thumbnail": "https://i.ytimg.com/vi/3VA_qTtnkt4/sddefault.jpg",
    "publishedAt": "2025-09-03T01:45:00Z",
    "viewCount": 2409,
    "duration": "PT5M59S"
  },
  {
    "videoId": "K4f-doflogY",
    "title": "오는 7/19일(토) 빌딩의신 세미나가 있습니다!",
    "thumbnail": "https://i.ytimg.com/vi/K4f-doflogY/sddefault.jpg",
    "publishedAt": "2025-07-04T03:00:26Z",
    "viewCount": 267,
    "duration": "PT1M14S"
  },
  {
    "videoId": "6sNiOs8L0NU",
    "title": "[데일리 이슈] 2024년 은행 대출 영업종료",
    "thumbnail": "https://i.ytimg.com/vi/6sNiOs8L0NU/sddefault.jpg",
    "publishedAt": "2024-11-04T00:45:00Z",
    "viewCount": 3070,
    "duration": "PT7M47S"
  },
  {
    "videoId": "87rM01W2QBk",
    "title": "한 달에 천만 원  최고급 실버타운이 있는 최고 상권 건대입구!  [대신 임장해드립니다 - 광진구 편]",
    "thumbnail": "https://i.ytimg.com/vi/87rM01W2QBk/sddefault.jpg",
    "publishedAt": "2024-12-07T03:00:04Z",
    "viewCount": 6573,
    "duration": "PT15M43S"
  },
  {
    "videoId": "WN6kfqxMEOg",
    "title": "10억 있으면 아파트 산다 VS 건물 산다",
    "thumbnail": "https://i.ytimg.com/vi/WN6kfqxMEOg/sddefault.jpg",
    "publishedAt": "2023-05-07T21:00:11Z",
    "viewCount": 30802,
    "duration": "PT10M48S"
  },
  {
    "videoId": "VemU7hpI7WA",
    "title": "올해 영끌족 어떡하냐...ㅣ240103 #빌딩의신 25번째 LIVE 소통방송",
    "thumbnail": "https://i.ytimg.com/vi/VemU7hpI7WA/sddefault.jpg",
    "publishedAt": "2024-01-03T18:24:25Z",
    "viewCount": 3579,
    "duration": "PT1H35M16S"
  },
  {
    "videoId": "24BJGbmjf8E",
    "title": "청화아파트 vs 삼풍아파트, 둘 중 어디 사면 되냐고?",
    "thumbnail": "https://i.ytimg.com/vi/24BJGbmjf8E/sddefault.jpg",
    "publishedAt": "2023-11-09T09:00:02Z",
    "viewCount": 8804,
    "duration": "PT4M17S"
  },
  {
    "videoId": "D0lDxzg0HGM",
    "title": "[빌딩의신 PM] '삼전동 랜드마크' 될 건물 공사 현장 다녀왔습니다!",
    "thumbnail": "https://i.ytimg.com/vi/D0lDxzg0HGM/sddefault.jpg",
    "publishedAt": "2023-08-30T21:00:07Z",
    "viewCount": 3168,
    "duration": "PT8M1S"
  },
  {
    "videoId": "YOVrz0sHJbY",
    "title": "[대신 임장해드립니다 - 강남구 1편] 도로 하나 차이로 건물 가격이 다르다?",
    "thumbnail": "https://i.ytimg.com/vi/YOVrz0sHJbY/sddefault.jpg",
    "publishedAt": "2024-02-25T03:00:16Z",
    "viewCount": 7441,
    "duration": "PT11M50S"
  },
  {
    "videoId": "oyMONSAOSgM",
    "title": "2025년 부동산투자_변화된 패러다임(투자 마인드) 4부",
    "thumbnail": "https://i.ytimg.com/vi/oyMONSAOSgM/sddefault.jpg",
    "publishedAt": "2024-11-15T00:55:00Z",
    "viewCount": 1120,
    "duration": "PT13M18S"
  },
  {
    "videoId": "xWHY_N1ODg0",
    "title": "나 같았으면 안샀을 이효리 신당동 건물투자 분석",
    "thumbnail": "https://i.ytimg.com/vi/xWHY_N1ODg0/sddefault.jpg",
    "publishedAt": "2023-02-23T21:00:22Z",
    "viewCount": 6765,
    "duration": "PT4M46S"
  },
  {
    "videoId": "iy61FFD_AYo",
    "title": "선 세게 넘은 재건축 아파트 분담금 폭탄",
    "thumbnail": "https://i.ytimg.com/vi/iy61FFD_AYo/sddefault.jpg",
    "publishedAt": "2024-03-01T06:00:18Z",
    "viewCount": 21053,
    "duration": "PT11M29S"
  },
  {
    "videoId": "CGyOftWGfYc",
    "title": "아마추어는 건물 살 때 이걸 본다 (건물투자 스터디 ep.1)",
    "thumbnail": "https://i.ytimg.com/vi/CGyOftWGfYc/sddefault.jpg",
    "publishedAt": "2024-01-06T03:00:06Z",
    "viewCount": 2570,
    "duration": "PT9M54S"
  },
  {
    "videoId": "-BeF1V6vYXU",
    "title": "아파트 이제는 59타입이 국민평형",
    "thumbnail": "https://i.ytimg.com/vi/-BeF1V6vYXU/sddefault.jpg",
    "publishedAt": "2024-03-06T10:00:00Z",
    "viewCount": 5114,
    "duration": "PT3M22S"
  },
  {
    "videoId": "B-g0XW5P0s8",
    "title": "(종로구 투자 핵심 요약) 이 세군데만 보세요",
    "thumbnail": "https://i.ytimg.com/vi/B-g0XW5P0s8/sddefault.jpg",
    "publishedAt": "2024-07-13T03:00:09Z",
    "viewCount": 1908,
    "duration": "PT7M39S"
  },
  {
    "videoId": "G5Wm4zMCAZc",
    "title": "[데일리 이슈] 국회, 대통령실 세종시로 이전? 제발 이번에는 정치인 분들 약속 지키세요!",
    "thumbnail": "https://i.ytimg.com/vi/G5Wm4zMCAZc/sddefault.jpg",
    "publishedAt": "2025-04-17T09:00:23Z",
    "viewCount": 7668,
    "duration": "PT5M57S"
  },
  {
    "videoId": "jL9xzrSVMzs",
    "title": "[위클리 이슈] 기업 파산 위험, 혼돈의 시기 냉정함을 찾자!",
    "thumbnail": "https://i.ytimg.com/vi/jL9xzrSVMzs/sddefault.jpg",
    "publishedAt": "2025-03-07T06:15:05Z",
    "viewCount": 6940,
    "duration": "PT12M3S"
  },
  {
    "videoId": "UdblIYcvRL4",
    "title": "유동인구 TOP! 선릉역 주변 충격적인 공실 상황!",
    "thumbnail": "https://i.ytimg.com/vi/UdblIYcvRL4/sddefault.jpg",
    "publishedAt": "2025-03-06T10:00:38Z",
    "viewCount": 89573,
    "duration": "PT7M13S"
  },
  {
    "videoId": "yLzN3JA1HMo",
    "title": "[대신 임장해드립니다-강남구 편] 강남에서 마지막 남은 빌딩투자 line, OO역에 주목하라 #학동역 #논현역 #빌딩매매",
    "thumbnail": "https://i.ytimg.com/vi/yLzN3JA1HMo/sddefault.jpg",
    "publishedAt": "2022-08-08T04:04:09Z",
    "viewCount": 1541,
    "duration": "PT6M37S"
  },
  {
    "videoId": "Sfkez0hq4iA",
    "title": "대치동 아파트, 학세권의 진짜 가치는? 보고서 완벽 해부!",
    "thumbnail": "https://i.ytimg.com/vi/Sfkez0hq4iA/sddefault.jpg",
    "publishedAt": "2025-03-19T10:00:40Z",
    "viewCount": 5701,
    "duration": "PT10M59S"
  },
  {
    "videoId": "2QWbt75_3sY",
    "title": "재건축 조합방식 VS 신탁방식 뭐가 다를까",
    "thumbnail": "https://i.ytimg.com/vi/2QWbt75_3sY/sddefault.jpg",
    "publishedAt": "2023-04-23T21:00:00Z",
    "viewCount": 5541,
    "duration": "PT3M24S"
  },
  {
    "videoId": "8XvtPaV4jso",
    "title": "[데일리 이슈] 드디어 투자할 때가 왔다 | 2025 경제성장률 1.8%, 여기가 추락의 끝!",
    "thumbnail": "https://i.ytimg.com/vi/8XvtPaV4jso/sddefault.jpg",
    "publishedAt": "2025-01-03T02:00:04Z",
    "viewCount": 4306,
    "duration": "PT10M54S"
  },
  {
    "videoId": "OpRFN4Bue0w",
    "title": "230712 #빌딩의신 12번째 LIVE 방송",
    "thumbnail": "https://i.ytimg.com/vi/OpRFN4Bue0w/sddefault.jpg",
    "publishedAt": "2023-07-12T13:32:18Z",
    "viewCount": 1727,
    "duration": "PT1H25M45S"
  },
  {
    "videoId": "4k9RQIGH2a0",
    "title": "부티플 건물투자 인터뷰 비하인드 스토리ㅣ빌딩의신",
    "thumbnail": "https://i.ytimg.com/vi/4k9RQIGH2a0/sddefault.jpg",
    "publishedAt": "2023-05-04T21:00:04Z",
    "viewCount": 791,
    "duration": "PT2M59S"
  },
  {
    "videoId": "DrxqVHsFMXc",
    "title": "오피스텔 vs 상가, 소액투자 고민되세요?",
    "thumbnail": "https://i.ytimg.com/vi/DrxqVHsFMXc/sddefault.jpg",
    "publishedAt": "2022-09-08T06:29:09Z",
    "viewCount": 2869,
    "duration": "PT8M4S"
  },
  {
    "videoId": "eBo4cR41Uqs",
    "title": "통일되면 평양 투자는 어디로? | 북한의 부촌 서평양",
    "thumbnail": "https://i.ytimg.com/vi/eBo4cR41Uqs/sddefault.jpg",
    "publishedAt": "2024-01-15T10:30:12Z",
    "viewCount": 1536,
    "duration": "PT8M35S"
  },
  {
    "videoId": "ay2fCVz7O-I",
    "title": "노후 리스크 줄이는 가장 효율적인 전략",
    "thumbnail": "https://i.ytimg.com/vi/ay2fCVz7O-I/sddefault.jpg",
    "publishedAt": "2024-05-18T03:00:02Z",
    "viewCount": 1479,
    "duration": "PT6M35S"
  },
  {
    "videoId": "pyN54yrWCSQ",
    "title": "아파트 공급이 부족하긴 뭐가 부족해요",
    "thumbnail": "https://i.ytimg.com/vi/pyN54yrWCSQ/sddefault.jpg",
    "publishedAt": "2024-01-31T10:30:14Z",
    "viewCount": 1896,
    "duration": "PT3M35S"
  },
  {
    "videoId": "uv2BlC5hzT8",
    "title": "20년 빌딩전문가가가 말하는 건물 신축꿀팁 세가지",
    "thumbnail": "https://i.ytimg.com/vi/uv2BlC5hzT8/sddefault.jpg",
    "publishedAt": "2022-11-02T21:00:22Z",
    "viewCount": 434,
    "duration": "PT8M45S"
  },
  {
    "videoId": "-ormCrwgdAU",
    "title": "12월 서울 입주 물량 제로 아닙니다ㅣ빌딩의신",
    "thumbnail": "https://i.ytimg.com/vi/-ormCrwgdAU/sddefault.jpg",
    "publishedAt": "2023-12-04T10:30:00Z",
    "viewCount": 1245,
    "duration": "PT4M17S"
  },
  {
    "videoId": "tq1Gi35Nx-A",
    "title": "돈만 있으면 건물투자 쉬울 거 같죠? 쓴소리 좀 하겠습니다.",
    "thumbnail": "https://i.ytimg.com/vi/tq1Gi35Nx-A/sddefault.jpg",
    "publishedAt": "2022-10-06T08:00:30Z",
    "viewCount": 595,
    "duration": "PT3M10S"
  },
  {
    "videoId": "qGaA5aela1k",
    "title": "총선 이후 집값 상승 VS 하락?",
    "thumbnail": "https://i.ytimg.com/vi/qGaA5aela1k/sddefault.jpg",
    "publishedAt": "2024-05-04T03:00:34Z",
    "viewCount": 5334,
    "duration": "PT7M14S"
  },
  {
    "videoId": "cVtyTXs2i78",
    "title": "[데일리 이슈] 초강력 추가 부동산 대책 발표 임박! 각오하고 있었다?",
    "thumbnail": "https://i.ytimg.com/vi/cVtyTXs2i78/sddefault.jpg",
    "publishedAt": "2025-09-29T05:00:47Z",
    "viewCount": 16090,
    "duration": "PT14M33S"
  },
  {
    "videoId": "E9C02m0f2XQ",
    "title": "송승헌의 종각 빌딩 투자, 성공? 실패?",
    "thumbnail": "https://i.ytimg.com/vi/E9C02m0f2XQ/sddefault.jpg",
    "publishedAt": "2025-02-19T07:25:17Z",
    "viewCount": 1350,
    "duration": "PT7M36S"
  },
  {
    "videoId": "9oyEMl-E2FY",
    "title": "대치동에서 이런 매물이 나올 줄이야.. | 매매사례 분석",
    "thumbnail": "https://i.ytimg.com/vi/9oyEMl-E2FY/sddefault.jpg",
    "publishedAt": "2025-03-26T10:00:10Z",
    "viewCount": 4212,
    "duration": "PT10M1S"
  },
  {
    "videoId": "o2lXtebRqoM",
    "title": "고덕 vs 마포 어디가 상급지? | 동vs동",
    "thumbnail": "https://i.ytimg.com/vi/o2lXtebRqoM/sddefault.jpg",
    "publishedAt": "2025-05-25T00:00:49Z",
    "viewCount": 4330,
    "duration": "PT7M14S"
  },
  {
    "videoId": "dTrIw3b3sEA",
    "title": "[데일리 이슈] 9·7 공급대책, 서울 핵심지는 왜 제외됐나",
    "thumbnail": "https://i.ytimg.com/vi/dTrIw3b3sEA/sddefault.jpg",
    "publishedAt": "2025-09-24T00:00:55Z",
    "viewCount": 2283,
    "duration": "PT8M10S"
  },
  {
    "videoId": "SlZk8PHn5lc",
    "title": "스쳐 지나가는 월급통장, 돈 모으고 싶으면 '일급의 5%'만 기억하세요..",
    "thumbnail": "https://i.ytimg.com/vi/SlZk8PHn5lc/sddefault.jpg",
    "publishedAt": "2022-03-30T09:18:18Z",
    "viewCount": 324,
    "duration": "PT5M41S"
  }
]